CSVDataFrame/CSVDataFrame.py
CSVDataFrame/LittleFrame.py
CSVDataFrame/Vectorize.py
CSVDataFrame/__init__.py
CSVDataFrame/main.py
CSVDataFrame/utils_numbers.py
GSKpy/BasicGSK.py
GSKpy/GSK.py
GSKpy/Gained_Shared_Junior_R1R2R3.py
GSKpy/Gained_Shared_Middle_R1R2R3.py
GSKpy/Gained_Shared_Senior_R1R2R3.py
GSKpy/__init__.py
GSKpy/boundConstraint.py
GSKpy/cec_functions.py
GSKpy/viz.py
GSKpy-1.4.0.dist-info/METADATA
GSKpy-1.4.0.dist-info/WHEEL
GSKpy-1.4.0.dist-info/top_level.txt
GSKpy-1.4.0.dist-info/RECORD
