Metadata-Version: 2.1
Name: GSKpy
Version: 1.4.0
Summary: Gaining-sharing knowledge algorithm GSK continuous optimization framework
Home-page: https://github.com/ha2emnomer/GSKPy
Author: Hazem Nomer
Author-email: h.nomer@nu.edu.eg
License: UNKNOWN
Project-URL: Bug Tracker, https://github.com/ha2emnomer/GSKPy/issues
Platform: UNKNOWN
Classifier: Programming Language :: Python :: 3
Classifier: License :: OSI Approved :: MIT License
Classifier: Operating System :: OS Independent
Requires-Python: >=3.6
